jagg/__init__.py
jagg/circuits/__init__.py
jagg/circuits/dnnf.py
jagg-0.0.2.dist-info/LICENSE
jagg-0.0.2.dist-info/METADATA
jagg-0.0.2.dist-info/WHEEL
jagg-0.0.2.dist-info/top_level.txt
jagg-0.0.2.dist-info/RECORD
